{"schema_version":1,"diagnostics":[{"domain":"parse","severity":"error","lsp_severity":1,"message":"I was not expecting a newline here","trace_policy":"none","visibility":"public","primary_span":{"file":"<FIXTURE>","range":{"start":{"line":7,"character":0},"end":{"line":7,"character":1}},"line":8,"column":1,"byte_start":254,"byte_end":255,"label":"not a valid expression"},"related_information":[],"notes":[],"help":"expressions start with a value (number, string, variable), an operator, or a keyword like `if` or `case`","suggestions":[],"cause_chain":[],"machine_data":{},"rendered":"error: I was not expecting a newline here\n  │\n7 │     value =\n8 │   }\n  │ ^ not a valid expression\n  │\n  = help: expressions start with a value (number, string, variable), an operator, or a keyword like `if` or `case`\n  │\n  └─ <FIXTURE>:8:1\n\n"}]}
